autodl_ao/__init__.py
autodl_ao/version.py
autodl_ao/infrastructure/__init__.py
autodl_ao/infrastructure/ao.py
autodl_ao/infrastructure/do.py
autodl_ao-0.0.1.dist-info/LICENSE
autodl_ao-0.0.1.dist-info/METADATA
autodl_ao-0.0.1.dist-info/WHEEL
autodl_ao-0.0.1.dist-info/top_level.txt
autodl_ao-0.0.1.dist-info/RECORD
